src/__init__.py
src/main.py
xcode2tuist-0.1.0.dist-info/METADATA
xcode2tuist-0.1.0.dist-info/WHEEL
xcode2tuist-0.1.0.dist-info/entry_points.txt
xcode2tuist-0.1.0.dist-info/licenses/LICENSE
xcode2tuist-0.1.0.dist-info/RECORD
