Metadata-Version: 2.4
Name: xcode2tuist
Version: 0.1.0
Summary: Convert Xcode projects to Tuist project descriptions
Project-URL: Homepage, https://github.com/saik0s/xcode2tuist
Project-URL: Documentation, https://github.com/saik0s/xcode2tuist#readme
Project-URL: Repository, https://github.com/saik0s/xcode2tuist.git
Author-email: Igor Tarasenko <tarasenko.igor.v@gmail.com>
License-Expression: MIT
License-File: LICENSE
Keywords: ios,project-generation,tuist,xcode
Classifier: Development Status :: 3 - Alpha
Classifier: Intended Audience :: Developers
Classifier: License :: OSI Approved :: MIT License
Classifier: Programming Language :: Python :: 3
Classifier: Programming Language :: Python :: 3.12
Classifier: Topic :: Software Development :: Build Tools
Requires-Python: >=3.12
Requires-Dist: pbxproj>=4.2.1
Requires-Dist: rich>=13.9.4
